napari_tyssue/__init__.py
napari_tyssue/_reader.py
napari_tyssue/_sample_data.py
napari_tyssue/_widget.py
napari_tyssue/_writer.py
napari_tyssue/apoptosis.py
napari_tyssue/cell_division_3d.py
napari_tyssue/cell_division_3d_v2.py
napari_tyssue/invagination.py
napari_tyssue/napari.yaml
napari_tyssue/tyssuewidget.py
napari_tyssue/_tests/__init__.py
napari_tyssue/_tests/test_sample_data.py
napari_tyssue/_tests/test_widget.py
napari_tyssue-0.1.2.dist-info/LICENSE
napari_tyssue-0.1.2.dist-info/METADATA
napari_tyssue-0.1.2.dist-info/WHEEL
napari_tyssue-0.1.2.dist-info/entry_points.txt
napari_tyssue-0.1.2.dist-info/top_level.txt
napari_tyssue-0.1.2.dist-info/RECORD
