Metadata-Version: 2.1
Name: napari-tyssue
Version: 0.1.2
Summary: A napari plugin for use with the tyssue library
Home-page: https://github.com/kephale/napari-tyssue
Author: Kyle Harrington
Author-email: czi@kyleharrington.com
License: BSD-3-Clause
Project-URL: Bug Tracker, https://github.com/kephale/napari-tyssue/issues
Project-URL: Documentation, https://github.com/kephale/napari-tyssue#README.md
Project-URL: Source Code, https://github.com/kephale/napari-tyssue
Project-URL: User Support, https://github.com/kephale/napari-tyssue/issues
Classifier: Development Status :: 2 - Pre-Alpha
Classifier: Framework :: napari
Classifier: Intended Audience :: Developers
Classifier: License :: OSI Approved :: BSD License
Classifier: Operating System :: OS Independent
Classifier: Programming Language :: Python
Classifier: Programming Language :: Python :: 3
Classifier: Programming Language :: Python :: 3 :: Only
Classifier: Programming Language :: Python :: 3.8
Classifier: Programming Language :: Python :: 3.9
Classifier: Programming Language :: Python :: 3.10
Classifier: Topic :: Scientific/Engineering :: Image Processing
Requires-Python: >=3.8
License-File: LICENSE
Requires-Dist: numpy
Requires-Dist: magicgui
Requires-Dist: qtpy
Requires-Dist: tyssue
Requires-Dist: quantities
Requires-Dist: pooch
Requires-Dist: tables
Requires-Dist: imageio-ffmpeg
Requires-Dist: invagination (==0.0.2)
Provides-Extra: testing
Requires-Dist: tox ; extra == 'testing'
Requires-Dist: pytest ; extra == 'testing'
Requires-Dist: pytest-cov ; extra == 'testing'
Requires-Dist: pytest-qt ; extra == 'testing'
Requires-Dist: napari ; extra == 'testing'
Requires-Dist: pyqt5 ; extra == 'testing'
